bsd/__main__.py
bsd/classes.py
bsd/clients.py
bsd/clocked.py
bsd/command.py
bsd/decoder.py
bsd/default.py
bsd/encoder.py
bsd/errored.py
bsd/handler.py
bsd/listens.py
bsd/loggers.py
bsd/message.py
bsd/objects.py
bsd/persist.py
bsd/repeats.py
bsd/runtime.py
bsd/scanner.py
bsd/skipper.py
bsd/threads.py
bsd/utility.py
bsd-2.data/scripts/bsd
bsd-2.dist-info/METADATA
bsd-2.dist-info/WHEEL
bsd-2.dist-info/top_level.txt
bsd-2.dist-info/zip-safe
bsd-2.dist-info/RECORD
