Metadata-Version: 2.1
Name: bsd
Version: 2
Summary: bsd is not berkely
Home-page: http://github.com/thatebhj/bsd
Author: Bart Thate
Author-email: thatebhj@gmail.com
License: Public Domain
Platform: UNKNOWN
Classifier: Development Status :: 3 - Alpha
Classifier: License :: Public Domain
Classifier: Operating System :: POSIX :: Linux
Classifier: Programming Language :: Python :: 3 :: Only
Classifier: Topic :: Software Development :: Libraries :: Python Modules
